pyindia_stock/__init__.py
pyindia_stock/stock_analysis.py
pyindia_stock-0.0.1.data/scripts/pyindia_stock
pyindia_stock-0.0.1.dist-info/LICENSE
pyindia_stock-0.0.1.dist-info/METADATA
pyindia_stock-0.0.1.dist-info/WHEEL
pyindia_stock-0.0.1.dist-info/top_level.txt
pyindia_stock-0.0.1.dist-info/RECORD
