Metadata-Version: 2.1
Name: pyindia-stock
Version: 0.0.1
Summary: Stock Prediction using FBProphet
Home-page: https://github.com/Shivananmn/pyindia-stock
Author: Shivanand
Author-email: shivanandnaduvin@gmail.com
License: MIT License
Platform: UNKNOWN
Requires-Python: >3.5.2
Requires-Dist: fbprophet (>=0.7.1)
